<?xml version="1.0" encoding="UTF-8"?>
<mxfile host="app.diagrams.net" agent="Mozilla/5.0 (Windows NT 10.0; Win64; x64) AppleWebKit/537.36 (KHTML, like Gecko) Chrome/127.0.0.0 Safari/537.36 Edg/127.0.0.0" version="24.7.7">
  <diagram id="j2_C4gLJk_HeaDmi43oK" name="Page-1">
    <mxGraphModel dx="2626" dy="791" grid="0" gridSize="10" guides="1" tooltips="1" connect="1" arrows="1" fold="1" page="0" pageScale="1" pageWidth="827" pageHeight="1169" background="none" math="1" shadow="0">
      <root>
        <mxCell id="X5NqExCQtvZxIxQ7pmgY-0" />
        <mxCell id="1" parent="X5NqExCQtvZxIxQ7pmgY-0" />
        <object label="CTI Clínica" id="Gr0Zq-AI6Quabplr0KPa-98">
          <mxCell style="ellipse;whiteSpace=wrap;strokeWidth=2;fillColor=#EDF5FF;fontSize=15;strokeColor=none;container=0;verticalAlign=top;spacingBottom=0;spacingTop=4;fontStyle=1;fontColor=default;metaEdit=0;comic=0;gradientColor=none;html=1;" parent="1" vertex="1">
            <mxGeometry x="-991" y="90.59" width="607" height="383" as="geometry">
              <mxRectangle x="-576" y="218" width="250" height="60" as="alternateBounds" />
            </mxGeometry>
          </mxCell>
        </object>
        <object label="" placeholders="1" id="Gr0Zq-AI6Quabplr0KPa-102">
          <mxCell style="image;html=1;image=img/lib/clip_art/computers/Monitor_Tower_128x128.png;fontFamily=Helvetica;fontSize=12;fontColor=#0A3DA3;align=center;strokeWidth=2;fillColor=#EDF5FF;fontStyle=1;verticalAlign=bottom;strokeColor=none;labelBackgroundColor=#EDF5FF;labelBorderColor=none;labelPosition=center;verticalLabelPosition=top;comic=0;" parent="1" vertex="1">
            <mxGeometry x="-875" y="269.6551467710372" width="98.43" height="84.82213307240704" as="geometry" />
          </mxCell>
        </object>
        <object label="" placeholders="1" id="q1g0-_doTiqwT4nAZ2be-11">
          <mxCell style="image;html=1;image=img/lib/clip_art/computers/Monitor_Tower_128x128.png;fontFamily=Helvetica;fontSize=12;fontColor=#0A3DA3;align=center;strokeWidth=2;fillColor=#EDF5FF;fontStyle=1;verticalAlign=bottom;strokeColor=none;labelBackgroundColor=#EDF5FF;labelBorderColor=none;labelPosition=center;verticalLabelPosition=top;comic=0;" parent="1" vertex="1">
            <mxGeometry x="-904.64" y="172.96868884540118" width="80.64" height="82.58109589041096" as="geometry" />
          </mxCell>
        </object>
        <object label="" placeholders="1" id="q1g0-_doTiqwT4nAZ2be-13">
          <mxCell style="image;html=1;image=img/lib/clip_art/computers/Monitor_Tower_128x128.png;fontFamily=Helvetica;fontSize=12;fontColor=#0A3DA3;align=center;strokeWidth=2;fillColor=#EDF5FF;fontStyle=1;verticalAlign=bottom;strokeColor=none;labelBackgroundColor=#EDF5FF;labelBorderColor=none;labelPosition=center;verticalLabelPosition=top;comic=0;" parent="1" vertex="1">
            <mxGeometry x="-796" y="144.00236790606655" width="83" height="86.19373776908023" as="geometry" />
          </mxCell>
        </object>
        <object label="" placeholders="1" id="q1g0-_doTiqwT4nAZ2be-15">
          <mxCell style="image;html=1;image=img/lib/clip_art/computers/Monitor_Tower_128x128.png;fontFamily=Helvetica;fontSize=12;fontColor=#0A3DA3;align=center;strokeWidth=2;fillColor=#EDF5FF;fontStyle=1;verticalAlign=bottom;strokeColor=none;labelBackgroundColor=#EDF5FF;labelBorderColor=none;labelPosition=center;verticalLabelPosition=top;comic=0;" parent="1" vertex="1">
            <mxGeometry x="-683" y="174.99868884540118" width="81" height="85.44422700587084" as="geometry" />
          </mxCell>
        </object>
        <mxCell id="q1g0-_doTiqwT4nAZ2be-18" value="" style="image;html=1;image=img/lib/clip_art/computers/Printer_Commercial_128x128.png" parent="1" vertex="1">
          <mxGeometry x="-713.0037558685447" y="289.99774413147713" width="88.34272300469483" height="117.07819905213272" as="geometry" />
        </mxCell>
        <mxCell id="q1g0-_doTiqwT4nAZ2be-19" value="" style="verticalLabelPosition=bottom;sketch=0;aspect=fixed;html=1;verticalAlign=top;strokeColor=none;align=center;outlineConnect=0;shape=mxgraph.citrix.ip_phone;" parent="1" vertex="1">
          <mxGeometry x="-572" y="290.00068493150684" width="77.48442270058709" height="37.47553816046967" as="geometry" />
        </mxCell>
        <object label="" placeholders="1" id="q1g0-_doTiqwT4nAZ2be-21">
          <mxCell style="image;html=1;image=img/lib/clip_art/computers/Monitor_Tower_128x128.png;fontFamily=Helvetica;fontSize=12;fontColor=#0A3DA3;align=center;strokeWidth=2;fillColor=#EDF5FF;fontStyle=1;verticalAlign=bottom;strokeColor=none;labelBackgroundColor=#EDF5FF;labelBorderColor=none;labelPosition=center;verticalLabelPosition=top;comic=0;" parent="1" vertex="1">
            <mxGeometry x="-572" y="168.9979256360078" width="97" height="77.19960861056751" as="geometry" />
          </mxCell>
        </object>
        <object label="CTI Cirúrgica" id="q1g0-_doTiqwT4nAZ2be-23">
          <mxCell style="ellipse;whiteSpace=wrap;strokeWidth=2;fillColor=#EDF5FF;fontSize=15;strokeColor=none;container=0;verticalAlign=top;spacingBottom=0;spacingTop=4;fontStyle=1;fontColor=default;metaEdit=0;comic=0;gradientColor=none;html=1;" parent="1" vertex="1">
            <mxGeometry x="-332" y="100" width="607" height="383" as="geometry">
              <mxRectangle x="-576" y="218" width="250" height="60" as="alternateBounds" />
            </mxGeometry>
          </mxCell>
        </object>
        <object label="" placeholders="1" id="q1g0-_doTiqwT4nAZ2be-24">
          <mxCell style="image;html=1;image=img/lib/clip_art/computers/Monitor_Tower_128x128.png;fontFamily=Helvetica;fontSize=12;fontColor=#0A3DA3;align=center;strokeWidth=2;fillColor=#EDF5FF;fontStyle=1;verticalAlign=bottom;strokeColor=none;labelBackgroundColor=#EDF5FF;labelBorderColor=none;labelPosition=center;verticalLabelPosition=top;comic=0;" parent="1" vertex="1">
            <mxGeometry x="-216" y="279.06514677103723" width="98.43" height="84.82213307240704" as="geometry" />
          </mxCell>
        </object>
        <object label="" placeholders="1" id="q1g0-_doTiqwT4nAZ2be-25">
          <mxCell style="image;html=1;image=img/lib/clip_art/computers/Monitor_Tower_128x128.png;fontFamily=Helvetica;fontSize=12;fontColor=#0A3DA3;align=center;strokeWidth=2;fillColor=#EDF5FF;fontStyle=1;verticalAlign=bottom;strokeColor=none;labelBackgroundColor=#EDF5FF;labelBorderColor=none;labelPosition=center;verticalLabelPosition=top;comic=0;" parent="1" vertex="1">
            <mxGeometry x="-245.64" y="182.37868884540117" width="80.64" height="82.58109589041096" as="geometry" />
          </mxCell>
        </object>
        <object label="" placeholders="1" id="q1g0-_doTiqwT4nAZ2be-26">
          <mxCell style="image;html=1;image=img/lib/clip_art/computers/Monitor_Tower_128x128.png;fontFamily=Helvetica;fontSize=12;fontColor=#0A3DA3;align=center;strokeWidth=2;fillColor=#EDF5FF;fontStyle=1;verticalAlign=bottom;strokeColor=none;labelBackgroundColor=#EDF5FF;labelBorderColor=none;labelPosition=center;verticalLabelPosition=top;comic=0;" parent="1" vertex="1">
            <mxGeometry x="-137" y="153.41236790606655" width="83" height="86.19373776908023" as="geometry" />
          </mxCell>
        </object>
        <object label="" placeholders="1" id="q1g0-_doTiqwT4nAZ2be-27">
          <mxCell style="image;html=1;image=img/lib/clip_art/computers/Monitor_Tower_128x128.png;fontFamily=Helvetica;fontSize=12;fontColor=#0A3DA3;align=center;strokeWidth=2;fillColor=#EDF5FF;fontStyle=1;verticalAlign=bottom;strokeColor=none;labelBackgroundColor=#EDF5FF;labelBorderColor=none;labelPosition=center;verticalLabelPosition=top;comic=0;" parent="1" vertex="1">
            <mxGeometry x="-24" y="184.40868884540117" width="81" height="85.44422700587084" as="geometry" />
          </mxCell>
        </object>
        <mxCell id="q1g0-_doTiqwT4nAZ2be-28" value="" style="image;html=1;image=img/lib/clip_art/computers/Printer_Commercial_128x128.png" parent="1" vertex="1">
          <mxGeometry x="-54.00375586854466" y="299.40774413147716" width="88.34272300469483" height="117.07819905213272" as="geometry" />
        </mxCell>
        <mxCell id="q1g0-_doTiqwT4nAZ2be-29" value="" style="verticalLabelPosition=bottom;sketch=0;aspect=fixed;html=1;verticalAlign=top;strokeColor=none;align=center;outlineConnect=0;shape=mxgraph.citrix.ip_phone;" parent="1" vertex="1">
          <mxGeometry x="87" y="299.41068493150686" width="77.48442270058709" height="37.47553816046967" as="geometry" />
        </mxCell>
        <object label="" placeholders="1" id="q1g0-_doTiqwT4nAZ2be-30">
          <mxCell style="image;html=1;image=img/lib/clip_art/computers/Monitor_Tower_128x128.png;fontFamily=Helvetica;fontSize=12;fontColor=#0A3DA3;align=center;strokeWidth=2;fillColor=#EDF5FF;fontStyle=1;verticalAlign=bottom;strokeColor=none;labelBackgroundColor=#EDF5FF;labelBorderColor=none;labelPosition=center;verticalLabelPosition=top;comic=0;" parent="1" vertex="1">
            <mxGeometry x="87" y="178.4079256360078" width="97" height="77.19960861056751" as="geometry" />
          </mxCell>
        </object>
      </root>
    </mxGraphModel>
  </diagram>
</mxfile>
